humid-0.3.1.dist-info/METADATA
humid-0.3.1.dist-info/WHEEL
humid-0.3.1.dist-info/entry_points.txt
humid-0.3.1.dist-info/licenses/LICENSE
humid/__init__.py
humid/__main__.py
humid/_words/__init__.py
humid/_words/ages.py
humid/_words/animals.py
humid/_words/colors.py
humid/_words/materials.py
humid/_words/opinions.py
humid/_words/origins.py
humid/_words/pokemons.py
humid/_words/purposes.py
humid/_words/quantities.py
humid/_words/shapes.py
humid/_words/sizes.py
humid/cli.py
humid/core.py
humid-0.3.1.dist-info/RECORD
