Metadata-Version: 2.1
Name: humid
Version: 0.3.1
Summary: Human Friendly UUIDs that are readable and pronounceable.
Keywords: UUID,ID,identifier,unique,readable,human friendly,pronouncable,adjective,word,noun
Author-Email: "W. Meijer" <houterm+humid@gmail.com>
License: MIT
Classifier: Programming Language :: Python :: 3
Requires-Python: >=3.9
Requires-Dist: typing-extensions>=4.12.2
Requires-Dist: pytest>=8.3.2; extra == "dev"
Requires-Dist: pre-commit>=3.5.0; extra == "dev"
Requires-Dist: uniplot>=0.14.1; extra == "dev"
Requires-Dist: mkdocs-material>=9.5.33; extra == "docs"
Requires-Dist: mkdocstrings-python>=1.10.9; extra == "docs"
Provides-Extra: dev
Provides-Extra: docs
